README.md
setup.py
csv_tool/__init__.py
django_csv_tool.egg-info/PKG-INFO
django_csv_tool.egg-info/SOURCES.txt
django_csv_tool.egg-info/dependency_links.txt
django_csv_tool.egg-info/requires.txt
django_csv_tool.egg-info/top_level.txt