Metadata-Version: 1.0
Name: django-csv-tool
Version: 0.3.9
Summary: Tool to help create CSV imports faster
Home-page: https://bitbucket.org/freakypie/django-csv-tool
Author: John Leith
Author-email: leith.john@gmail.com
License: UNKNOWN
Platform: UNKNOWN
